LICENSE
MANIFEST.in
README.rst
setup.py
AAEI/AAEI.py
AAEI/AEI.py
AAEI/AEI_PV.py
AAEI/__init__.py
AAEI/bpaei.py
AAEI/genra_C10H16.csv
AAEI/genra_CH2O.csv
AAEI/genra_NO2.csv
AAEI/genra_O3.csv
AAEI/genra_SO2.csv
aaei.egg-info/PKG-INFO
aaei.egg-info/SOURCES.txt
aaei.egg-info/dependency_links.txt
aaei.egg-info/entry_points.txt
aaei.egg-info/not-zip-safe
aaei.egg-info/requires.txt
aaei.egg-info/top_level.txt