Metadata-Version: 2.1
Name: aaei
Version: 1.5.0
Summary: Air Adverse Effect Index
Home-page: http://github.com/Kwabratseur/AAEI
Author: Jeroen van 't Ende
Author-email: jeroen.vantende@outlook.com
License: MIT
Keywords: trace gas compound toxicity read-across statistics health index
Platform: UNKNOWN
Classifier: Development Status :: 3 - Alpha
Classifier: License :: OSI Approved :: MIT License
Classifier: Programming Language :: Python :: 3.9
Classifier: Programming Language :: Python :: 3.10
Classifier: Topic :: Scientific/Engineering :: Atmospheric Science
Classifier: Intended Audience :: Science/Research
Classifier: Intended Audience :: Education
Provides-Extra: Viz
License-File: LICENSE
